corgy/__init__.py
corgy/_actions.py
corgy/_annotations.py
corgy/_corgy.py
corgy/_corgychecker.py
corgy/_corgyparser.py
corgy/_enum.py
corgy/_helpfmt.py
corgy/_meta.py
corgy/_version.py
corgy/py.typed
corgy/types/__init__.py
corgy/types/_expand.py
corgy/types/_initargs.py
corgy/types/_inputfile.py
corgy/types/_keyvaluepairs.py
corgy/types/_outputfile.py
corgy/types/_subclass.py
corgy-9.3.0.dist-info/LICENSE
corgy-9.3.0.dist-info/METADATA
corgy-9.3.0.dist-info/WHEEL
corgy-9.3.0.dist-info/RECORD
