Metadata-Version: 2.1
Name: corgy
Version: 9.3.0
Summary: Elegant data classes
Home-page: https://github.com/jayanthkoushik/corgy
License: MIT
Keywords: data classes,argparse,argument parsing,command line parsing,cli
Author: Jayanth Koushik
Author-email: mail@jkoushik.me
Requires-Python: >=3.7,<4.0
Classifier: Development Status :: 5 - Production/Stable
Classifier: Intended Audience :: Developers
Classifier: License :: OSI Approved :: MIT License
Classifier: Natural Language :: English
Classifier: Operating System :: OS Independent
Classifier: Programming Language :: Python :: 3
Classifier: Programming Language :: Python :: 3.7
Classifier: Programming Language :: Python :: 3.8
Classifier: Programming Language :: Python :: 3.9
Classifier: Programming Language :: Python :: 3.10
Classifier: Programming Language :: Python :: 3.11
Classifier: Programming Language :: Python :: 3.12
Classifier: Topic :: Software Development :: User Interfaces
Classifier: Topic :: Utilities
Provides-Extra: colors
Provides-Extra: toml
Requires-Dist: crayons (>=0.4.0,<0.5.0) ; extra == "colors"
Requires-Dist: tomli (>=2.0.1,<3.0.0) ; (python_version < "3.11") and (extra == "toml")
Requires-Dist: typing_extensions (>=4.0,<5.0) ; python_version < "3.11"
Project-URL: Repository, https://github.com/jayanthkoushik/corgy
